{
  "uuid": "b4599131-4b96-42d3-865d-af6a4859997c",
  "name": "ФискальныеОперации",
  "name2": {},
  "comment": "",
  "h1_0": "1",
  "h0": "3",
  "h5": [
    "1",
    "3",
    "9595ddd6-e72c-47ad-a156-672db811628c",
    "2",
    "13134205-f60b-11d5-a3c7-0050bae0a776",
    "2",
    "09c412e0-0f30-11d6-a3c7-0050bae0a776",
    "2",
    "3c1c25ab-8458-4f2b-8485-6471eb235795",
    "0"
  ],
  "data": [
    [
      "1",
      [
        "33",
        "d82e8e27-c9fd-4c3d-85ec-2e5cb4fe7133",
        "e0ab41e8-cd62-4af6-8dba-8d8fd245ded7",
        "1d5b3130-3e77-470b-803f-de18f1e97087",
        "85672a49-04bc-4d6c-bf2e-febae1b29180",
        "a8aa8e85-9d96-402d-ac5c-6b619286d68e",
        "34f0abe6-d398-4771-9af9-305a1331b32d",
        "2eca83c5-4cf7-4531-81f1-40b380f0850c",
        "1a41ddea-f1e6-4af5-83ac-57d756248fa8",
        "fc864eea-6404-426d-ae1b-d6d9612b01af",
        "63511685-a2f8-4242-9e52-1bc6249a167a",
        "00f3bfb3-ff06-4da0-b6a5-5e7500823947",
        "d27d8bb0-297c-4235-9f7a-c6552482f150",
        "08c7b86b-0d2a-4081-a089-9b1d2f1e8699",
        "6fd90374-8ce0-4e5c-a185-2d8fc223a5ff",
        [
          "0",
          [
            "3",
            [
              "1",
              "0",
              "b4599131-4b96-42d3-865d-af6a4859997c"
            ],
            "\"ФискальныеОперации\"",
            [
              "0"
            ],
            "\"\"",
            "1",
            "3",
            "9595ddd6-e72c-47ad-a156-672db811628c",
            "2",
            "13134205-f60b-11d5-a3c7-0050bae0a776",
            "2",
            "09c412e0-0f30-11d6-a3c7-0050bae0a776",
            "2",
            "3c1c25ab-8458-4f2b-8485-6471eb235795",
            "0"
          ]
        ],
        "00000000-0000-0000-0000-000000000000",
        "00000000-0000-0000-0000-000000000000",
        "0",
        "0",
        "1",
        "1",
        "0",
        "1",
        "1",
        "0",
        [
          "0"
        ],
        "00000000-0000-0000-0000-000000000000",
        "00000000-0000-0000-0000-000000000000",
        [
          "0"
        ],
        [
          "0"
        ],
        [
          "0"
        ],
        [
          "0"
        ],
        [
          "0"
        ],
        "0",
        "0",
        "0",
        "0",
        "0"
      ],
      "6",
      [
        "13134202-f60b-11d5-a3c7-0050bae0a776",
        "4",
        [
          [
            "7",
            [
              "27",
              [
                "2",
                [
                  "3",
                  [
                    "1",
                    "0",
                    "e0b69b2f-9fa1-4160-9c7f-1c30c5b54937"
                  ],
                  "\"НомерЧекаККМ\"",
                  [
                    "0"
                  ],
                  "\"\"",
                  "1",
                  "2",
                  "9595ddd6-e72c-47ad-a156-672db811628c",
                  "2",
                  "b1053250-abe6-11d4-9434-004095e12fc7",
                  "2",
                  "e21067d4-d826-4375-acba-7c91efebe502",
                  "0"
                ],
                [
                  "\"Pattern\"",
                  [
                    "\"N\"",
                    "8",
                    "0",
                    "0"
                  ]
                ]
              ],
              "0",
              [
                "0"
              ],
              [
                "0"
              ],
              "0",
              "\"\"",
              "0",
              [
                "\"U\""
              ],
              [
                "\"U\""
              ],
              "0",
              "00000000-0000-0000-0000-000000000000",
              "2",
              "0",
              [
                "5006",
                "0"
              ],
              [
                "3",
                "0",
                "0"
              ],
              [
                "0",
                "0"
              ],
              "0",
              [
                "0"
              ],
              [
                "\"S\"",
                "\"\""
              ],
              "0",
              "0",
              "0"
            ],
            "0",
            "1",
            "1"
          ],
          "0"
        ],
        [
          [
            "7",
            [
              "27",
              [
                "2",
                [
                  "3",
                  [
                    "1",
                    "0",
                    "ea0c7ab0-2762-4276-90c3-59446da98b02"
                  ],
                  "\"НомерСменыККМ\"",
                  [
                    "0"
                  ],
                  "\"\"",
                  "1",
                  "2",
                  "9595ddd6-e72c-47ad-a156-672db811628c",
                  "2",
                  "b1053250-abe6-11d4-9434-004095e12fc7",
                  "2",
                  "84cc7c8d-7e84-4a02-97dd-d7aa83817ebc",
                  "0"
                ],
                [
                  "\"Pattern\"",
                  [
                    "\"N\"",
                    "10",
                    "0",
                    "0"
                  ]
                ]
              ],
              "0",
              [
                "0"
              ],
              [
                "0"
              ],
              "0",
              "\"\"",
              "0",
              [
                "\"U\""
              ],
              [
                "\"U\""
              ],
              "0",
              "00000000-0000-0000-0000-000000000000",
              "2",
              "0",
              [
                "5006",
                "0"
              ],
              [
                "3",
                "0",
                "0"
              ],
              [
                "0",
                "0"
              ],
              "0",
              [
                "0"
              ],
              [
                "\"S\"",
                "\"\""
              ],
              "0",
              "0",
              "0"
            ],
            "0",
            "1",
            "1"
          ],
          "0"
        ],
        [
          [
            "7",
            [
              "27",
              [
                "2",
                [
                  "3",
                  [
                    "1",
                    "0",
                    "c5120796-f3f6-4ed4-823d-d6bbfcadd421"
                  ],
                  "\"РегистрационныйНомерККТ\"",
                  [
                    "0"
                  ],
                  "\"\"",
                  "1",
                  "2",
                  "9595ddd6-e72c-47ad-a156-672db811628c",
                  "2",
                  "b1053250-abe6-11d4-9434-004095e12fc7",
                  "2",
                  "2d997c3a-d807-4b31-9589-062cbca23937",
                  "0"
                ],
                [
                  "\"Pattern\"",
                  [
                    "\"S\"",
                    "20",
                    "1"
                  ]
                ]
              ],
              "0",
              [
                "0"
              ],
              [
                "0"
              ],
              "0",
              "\"\"",
              "0",
              [
                "\"U\""
              ],
              [
                "\"U\""
              ],
              "0",
              "00000000-0000-0000-0000-000000000000",
              "2",
              "0",
              [
                "5006",
                "0"
              ],
              [
                "3",
                "0",
                "0"
              ],
              [
                "0",
                "0"
              ],
              "0",
              [
                "0"
              ],
              [
                "\"S\"",
                "\"\""
              ],
              "0",
              "0",
              "0"
            ],
            "0",
            "1",
            "1"
          ],
          "0"
        ],
        [
          [
            "7",
            [
              "27",
              [
                "2",
                [
                  "3",
                  [
                    "1",
                    "0",
                    "aba87ce8-1f04-42d0-a8d7-ba6c4914aeba"
                  ],
                  "\"ДанныеXML\"",
                  [
                    "0"
                  ],
                  "\"\"",
                  "1",
                  "2",
                  "9595ddd6-e72c-47ad-a156-672db811628c",
                  "2",
                  "b1053250-abe6-11d4-9434-004095e12fc7",
                  "2",
                  "6e144419-519f-477d-9eac-13f51ab2817d",
                  "0"
                ],
                [
                  "\"Pattern\"",
                  [
                    "\"#\"",
                    "e199ca70-93cf-46ce-a54b-6edc88c3a296"
                  ]
                ]
              ],
              "0",
              [
                "0"
              ],
              [
                "0"
              ],
              "0",
              "\"\"",
              "0",
              [
                "\"U\""
              ],
              [
                "\"U\""
              ],
              "0",
              "00000000-0000-0000-0000-000000000000",
              "2",
              "0",
              [
                "5006",
                "0"
              ],
              [
                "3",
                "0",
                "0"
              ],
              [
                "0",
                "0"
              ],
              "0",
              [
                "0"
              ],
              [
                "\"S\"",
                "\"\""
              ],
              "0",
              "0",
              "0"
            ],
            "0",
            "1",
            "1"
          ],
          "0"
        ]
      ],
      [
        "13134203-f60b-11d5-a3c7-0050bae0a776",
        "1",
        [
          [
            "9",
            [
              "27",
              [
                "2",
                [
                  "3",
                  [
                    "1",
                    "0",
                    "0512c51c-294b-45af-8c01-446b7068204f"
                  ],
                  "\"ДокументОснование\"",
                  [
                    "0"
                  ],
                  "\"\"",
                  "1",
                  "2",
                  "9595ddd6-e72c-47ad-a156-672db811628c",
                  "2",
                  "b1053250-abe6-11d4-9434-004095e12fc7",
                  "2",
                  "85c311f9-eaa5-4f91-8d8d-7385bfb79031",
                  "0"
                ],
                [
                  "\"Pattern\"",
                  [
                    "\"#\"",
                    "d1a8a7a9-b0b0-4e07-9aa6-833847cb6a8d"
                  ]
                ]
              ],
              "0",
              [
                "0"
              ],
              [
                "0"
              ],
              "0",
              "\"\"",
              "0",
              [
                "\"U\""
              ],
              [
                "\"U\""
              ],
              "0",
              "00000000-0000-0000-0000-000000000000",
              "2",
              "0",
              [
                "5006",
                "0"
              ],
              [
                "3",
                "0",
                "0"
              ],
              [
                "0",
                "0"
              ],
              "0",
              [
                "0"
              ],
              [
                "\"S\"",
                "\"\""
              ],
              "0",
              "0",
              "0"
            ],
            "0",
            "0",
            "0",
            "1",
            "1",
            "1"
          ],
          "0"
        ]
      ],
      [
        "13134204-f60b-11d5-a3c7-0050bae0a776",
        "0"
      ],
      [
        "3daea016-69b7-4ed4-9453-127911372fe6",
        "0"
      ],
      [
        "a2207540-1400-11d6-a3c7-0050bae0a776",
        "0"
      ],
      [
        "b44ba719-945c-445c-8aab-1088fa4df16e",
        "0"
      ]
    ]
  ]
}