{
  "uuid": "df9fce1f-f4d1-407d-aa40-52fc0c094bd6",
  "name": "РМК_Цифра9",
  "name2": {},
  "comment": "",
  "h1_0": "1",
  "h0": "3",
  "h5": [
    "1",
    "1",
    "9595ddd6-e72c-47ad-a156-672db811628c",
    "2",
    "3b9c9c49-5a3a-4df6-a8bb-2ae8f9a5281c",
    "0"
  ],
  "data": [
    [
      "1",
      [
        "4",
        [
          "3",
          [
            "1",
            "0",
            "df9fce1f-f4d1-407d-aa40-52fc0c094bd6"
          ],
          "\"РМК_Цифра9\"",
          [
            "0"
          ],
          "\"\"",
          "1",
          "1",
          "9595ddd6-e72c-47ad-a156-672db811628c",
          "2",
          "3b9c9c49-5a3a-4df6-a8bb-2ae8f9a5281c",
          "0"
        ],
        "0",
        "0"
      ],
      "0"
    ]
  ]
}